Metadata-Version: 2.1
Name: mpire
Version: 2.10.1
Summary: A Python package for easy multiprocessing, but faster than multiprocessing
Home-page: https://github.com/sybrenjansen/mpire
Author: Sybren Jansen
License: MIT
Platform: UNKNOWN
Classifier: Development Status :: 5 - Production/Stable
Classifier: Programming Language :: Python :: 3.8
Classifier: Programming Language :: Python :: 3.9
Classifier: Programming Language :: Python :: 3.10
Classifier: Programming Language :: Python :: 3.11
Classifier: Programming Language :: Python :: 3.12
Classifier: License :: OSI Approved :: MIT License
Classifier: Topic :: Software Development
Classifier: Topic :: Software Development :: Libraries
Classifier: Topic :: Software Development :: Libraries :: Python Modules
Requires-Dist: pygments (>=2.0)
Requires-Dist: tqdm (>=4.27)
Requires-Dist: pywin32 (>=301) ; platform_system == "Windows"
Requires-Dist: importlib-resources ; python_version < "3.9"
Provides-Extra: dashboard
Requires-Dist: flask ; extra == 'dashboard'
Provides-Extra: dill
Requires-Dist: multiprocess ; (python_version < "3.11") and extra == 'dill'
Requires-Dist: multiprocess (>=0.70.15) ; (python_version >= "3.11") and extra == 'dill'
Provides-Extra: docs
Requires-Dist: docutils (==0.17.1) ; extra == 'docs'
Requires-Dist: sphinx (==3.2.1) ; extra == 'docs'
Requires-Dist: sphinx-rtd-theme (==0.5.0) ; extra == 'docs'
Requires-Dist: sphinx-autodoc-typehints (==1.11.0) ; extra == 'docs'
Requires-Dist: sphinxcontrib-images (==0.9.2) ; extra == 'docs'
Requires-Dist: sphinx-versions (==1.0.1) ; extra == 'docs'
Provides-Extra: testing
Requires-Dist: ipywidgets ; extra == 'testing'
Requires-Dist: numpy ; extra == 'testing'
Requires-Dist: rich ; extra == 'testing'
Requires-Dist: pywin32 (>=301) ; (platform_system == "Windows") and extra == 'testing'
Requires-Dist: multiprocess ; (python_version < "3.11") and extra == 'testing'
Requires-Dist: multiprocess (>=0.70.15) ; (python_version >= "3.11") and extra == 'testing'
